{
  "books": [
    {
      "title": "Dark Tower",
      "id": 1
    },
    {
      "title": "ddd",
      "id": 2
    },
    {
      "title": "dd",
      "id": 3
    },
    {
      "title": "ff",
      "id": 4
    },
    {
      "title": "ff",
      "id": 5
    },
    {
      "title": "sfsdsd",
      "id": 6
    },
    {
      "title": "сс",
      "id": 7
    },
    {
      "title": "ссссс",
      "id": 8
    },
    {
      "title": "dd",
      "id": 9
    },
    {
      "title": "sdddd",
      "id": 10
    },
    {
      "title": "ff",
      "id": 11
    },
    {
      "title": "Harry Potter",
      "id": 12
    },
    {
      "title": "ddd",
      "id": 13
    },
    {
      "title": "ff",
      "id": 14
    },
    {
      "title": "dd",
      "id": 15
    },
    {
      "title": "dd",
      "id": 16
    },
    {
      "title": "ff",
      "id": 17
    },
    {
      "title": "ff",
      "id": 18
    },
    {
      "title": "dd",
      "id": 19
    },
    {
      "title": "dd",
      "id": 20
    },
    {
      "title": "fff",
      "id": 21
    },
    {
      "title": "f",
      "id": 22
    },
    {
      "title": "c",
      "id": 23
    },
    {
      "title": "ddd",
      "id": 24
    },
    {
      "title": "sss",
      "id": 25
    },
    {
      "title": "dddd",
      "id": 26
    },
    {
      "title": "dd",
      "id": 27
    }
  ]
}